ofanalysis/__init__.py
ofanalysis/analysis_helper.py
ofanalysis/const.py
ofanalysis/utility.py
ofanalysis/aks/__init__.py
ofanalysis/aks/akshare_data_update.py
ofanalysis/jiuquan/__init__.py
ofanalysis/jiuquan/fund_curve.py
ofanalysis/jiuquan/fund_data.py
ofanalysis/jiuquan/fund_info.py
ofanalysis/jiuquan/fund_manager.py
ofanalysis/jiuquan/fund_rank.py
ofanalysis/jiuquan/fund_rank_list.py
ofanalysis/jiuquan/fund_vest.py
ofanalysis/lixingren/__init__.py
ofanalysis/lixingren/lixingren_index_data.py
ofanalysis/lixingren/lixingren_sw_data.py
ofanalysis/morningstar/__init__.py
ofanalysis/morningstar/morning_star.py
ofanalysis/morningstar/mysnowflake.py
ofanalysis/notion/__init__.py
ofanalysis/notion/notion_update.py
ofanalysis/ts/__init__.py
ofanalysis/ts/ts_data_update.py
tests/__init__.py
tests/test_akshare_data_update.py
tests/test_analysis_helper.py
tests/test_fund_curve.py
tests/test_fund_data.py
tests/test_fund_info.py
tests/test_fund_manager.py
tests/test_fund_rank.py
tests/test_fund_rank_list.py
tests/test_fund_vest.py
tests/test_lixingren_index_data.py
tests/test_lixingren_sw_data.py
tests/test_morning_star.py
tests/test_notion_update.py
tests/test_ts_data_update.py
ofanalysis-0.3.0.dist-info/LICENSE
ofanalysis-0.3.0.dist-info/METADATA
ofanalysis-0.3.0.dist-info/WHEEL
ofanalysis-0.3.0.dist-info/top_level.txt
ofanalysis-0.3.0.dist-info/RECORD
