Metadata-Version: 2.1
Name: ofanalysis
Version: 0.3.0
Summary: A framework analysing open fund in China
Home-page: https://github.com/laye0619/ofanalysis
Author: LayeWang
Author-email: laye0619@gmail.com
License: UNKNOWN
Platform: UNKNOWN
Classifier: Programming Language :: Python :: 3
Classifier: License :: OSI Approved :: MIT License
Classifier: Operating System :: OS Independent
License-File: LICENSE
Requires-Dist: pandas
Requires-Dist: loguru
Requires-Dist: akshare
Requires-Dist: tushare
Requires-Dist: pymongo
Requires-Dist: pytz
Requires-Dist: requests
Requires-Dist: pyecharts
Requires-Dist: setuptools
Requires-Dist: bs4
Requires-Dist: beautifulsoup4
Requires-Dist: selenium
Requires-Dist: Pillow
Requires-Dist: numpy
